[{"name": "MTA-0925", "mark": 4.9835, "spot_price": 5.423, "diff": "0.439500", "rate": "8.10437%", "rate1": "8.10437"}, {"name": "RUNE-0925", "mark": 0.483, "spot_price": 0.4555, "diff": "0.0275000", "rate": "6.03732%", "rate1": "6.03732"}, {"name": "COMP-0925", "mark": 127.0, "spot_price": 135.025, "diff": "8.02500", "rate": "5.94334%", "rate1": "5.94334"}, {"name": "DMG-0925", "mark": 1.112, "spot_price": 1.062, "diff": "0.0500000", "rate": "4.70810%", "rate1": "4.70810"}, {"name": "BTC-1225", "mark": 11813.0, "spot_price": 11352.0, "diff": "461", "rate": "4.06096%", "rate1": "4.06096"}, {"name": "BAL-0925", "mark": 10.13, "spot_price": 10.55, "diff": "0.420000", "rate": "3.98104%", "rate1": "3.98104"}, {"name": "SXP-0925", "mark": 1.8325, "spot_price": 1.7755, "diff": "0.0570000", "rate": "3.21036%", "rate1": "3.21036"}, {"name": "BTMX-0925", "mark": 0.04885, "spot_price": 0.05042, "diff": "0.00157000", "rate": "3.11384%", "rate1": "3.11384"}, {"name": "BCH-0925", "mark": 309.85, "spot_price": 301.175, "diff": "8.67500", "rate": "2.88039%", "rate1": "2.88039"}, {"name": "LTC-0925", "mark": 59.8, "spot_price": 58.15, "diff": "1.65000", "rate": "2.83749%", "rate1": "2.83749"}, {"name": "ETH-0925", "mark": 356.28, "spot_price": 346.53, "diff": "9.75000", "rate": "2.81361%", "rate1": "2.81361"}, {"name": "SOL-0925", "mark": 1.5825, "spot_price": 1.545, "diff": "0.0375000", "rate": "2.42718%", "rate1": "2.42718"}, {"name": "TRX-0925", "mark": 0.0201325, "spot_price": 0.0196575, "diff": "0.000475000", "rate": "2.41638%", "rate1": "2.41638"}, {"name": "BTC-0925", "mark": 11604.0, "spot_price": 11352.0, "diff": "252", "rate": "2.21987%", "rate1": "2.21987"}, {"name": "PAXG-0925", "mark": 2012.0, "spot_price": 1979.3, "diff": "32.7000", "rate": "1.65210%", "rate1": "1.65210"}, {"name": "TRYB-0925", "mark": 0.13936, "spot_price": 0.14137, "diff": "0.00201000", "rate": "1.42180%", "rate1": "1.42180"}, {"name": "KNC-0925", "mark": 1.4846, "spot_price": 1.4664, "diff": "0.0182000", "rate": "1.24113%", "rate1": "1.24113"}, {"name": "XRP-0925", "mark": 0.26335, "spot_price": 0.260375, "diff": "0.00297500", "rate": "1.14258%", "rate1": "1.14258"}, {"name": "CUSDT-0925", "mark": 0.0203725, "spot_price": 0.020195, "diff": "0.000177500", "rate": "0.878930%", "rate1": "0.878930"}, {"name": "XAUT-0925", "mark": 1965.2, "spot_price": 1952.7, "diff": "12.5000", "rate": "0.640139%", "rate1": "0.640139"}, {"name": "USDT-0925", "mark": 0.9999, "spot_price": 1.001, "diff": "0.00110000", "rate": "0.109890%", "rate1": "0.109890"}, {"name": "MKR-0925", "mark": 557.0, "spot_price": 556.5, "diff": "0.5", "rate": "0.0898473%", "rate1": "0.0898473"}, {"name": "LINK-0925", "mark": 7.76, "spot_price": 7.762, "diff": "0.00200000", "rate": "0.0257666%", "rate1": "0.0257666"}, {"name": "BNB-0925", "mark": 20.66, "spot_price": 20.656, "diff": "0.00400000", "rate": "0.0193648%", "rate1": "0.0193648"}]