[{"name": "COMP-0925", "mark": 176.0, "spot_price": 295.55, "diff": "119.550", "rate": "40.4500%", "rate1": "40.4500"}, {"name": "TRYB-0925", "mark": 0.14099, "spot_price": 0.14408, "diff": "0.00309000", "rate": "2.14464%", "rate1": "2.14464"}, {"name": "COMP-0626", "mark": 254.0, "spot_price": 295.55, "diff": "41.5500", "rate": "14.0585%", "rate1": "14.0585"}, {"name": "KNC-0925", "mark": 1.2162, "spot_price": 1.2404, "diff": "0.0242000", "rate": "1.95098%", "rate1": "1.95098"}, {"name": "BTC-1225", "mark": 9593.5, "spot_price": 9415.5, "diff": "178.0", "rate": "1.89050%", "rate1": "1.89050"}, {"name": "BTMX-0925", "mark": 0.03769, "spot_price": 0.03839, "diff": "0.000700000", "rate": "1.82339%", "rate1": "1.82339"}, {"name": "CUSDT-0925", "mark": 0.0204325, "spot_price": 0.0201125, "diff": "0.000320000", "rate": "1.59105%", "rate1": "1.59105"}, {"name": "BTC-0925", "mark": 9528.0, "spot_price": 9415.5, "diff": "112.5", "rate": "1.19484%", "rate1": "1.19484"}, {"name": "ETH-0925", "mark": 237.69, "spot_price": 234.9, "diff": "2.79000", "rate": "1.18774%", "rate1": "1.18774"}, {"name": "BCH-0925", "mark": 238.7, "spot_price": 235.9, "diff": "2.80000", "rate": "1.18694%", "rate1": "1.18694"}, {"name": "LTC-0925", "mark": 43.97, "spot_price": 43.59, "diff": "0.380000", "rate": "0.871760%", "rate1": "0.871760"}, {"name": "TRYB-0626", "mark": 0.14512, "spot_price": 0.14408, "diff": "0.00104000", "rate": "0.721821%", "rate1": "0.721821"}, {"name": "BNB-0925", "mark": 16.075, "spot_price": 16.183, "diff": "0.108000", "rate": "0.667367%", "rate1": "0.667367"}, {"name": "PAXG-0925", "mark": 1759.6, "spot_price": 1748.6, "diff": "11.0000", "rate": "0.629075%", "rate1": "0.629075"}, {"name": "KNC-0626", "mark": 1.2335, "spot_price": 1.2404, "diff": "0.00690000", "rate": "0.556272%", "rate1": "0.556272"}, {"name": "TRX-0925", "mark": 0.0162275, "spot_price": 0.01615, "diff": "0.0000775000", "rate": "0.479876%", "rate1": "0.479876"}, {"name": "XAUT-0626", "mark": 1750.8, "spot_price": 1758.0, "diff": "7.20000", "rate": "0.409556%", "rate1": "0.409556"}, {"name": "PAXG-0626", "mark": 1753.3, "spot_price": 1748.6, "diff": "4.70000", "rate": "0.268786%", "rate1": "0.268786"}, {"name": "BTC-0626", "mark": 9436.5, "spot_price": 9415.5, "diff": "21.0", "rate": "0.223036%", "rate1": "0.223036"}, {"name": "BTMX-0626", "mark": 0.03847, "spot_price": 0.03839, "diff": "0.0000800000", "rate": "0.208388%", "rate1": "0.208388"}, {"name": "ETH-0626", "mark": 235.38, "spot_price": 234.9, "diff": "0.480000", "rate": "0.204342%", "rate1": "0.204342"}, {"name": "XAUT-0925", "mark": 1761.1, "spot_price": 1758.0, "diff": "3.10000", "rate": "0.176337%", "rate1": "0.176337"}, {"name": "LTC-0626", "mark": 43.65, "spot_price": 43.59, "diff": "0.0600000", "rate": "0.137646%", "rate1": "0.137646"}, {"name": "BNB-0626", "mark": 16.1625, "spot_price": 16.183, "diff": "0.0205000", "rate": "0.126676%", "rate1": "0.126676"}, {"name": "BCH-0626", "mark": 236.15, "spot_price": 235.9, "diff": "0.250000", "rate": "0.105977%", "rate1": "0.105977"}, {"name": "TRX-0626", "mark": 0.016135, "spot_price": 0.01615, "diff": "0.0000150000", "rate": "0.0928793%", "rate1": "0.0928793"}, {"name": "USDT-0925", "mark": 0.9999, "spot_price": 0.9993, "diff": "0.000600000", "rate": "0.0600420%", "rate1": "0.0600420"}, {"name": "LINK-0925", "mark": 4.3505, "spot_price": 4.349, "diff": "0.00150000", "rate": "0.0344907%", "rate1": "0.0344907"}, {"name": "CUSDT-0626", "mark": 0.0201175, "spot_price": 0.0201125, "diff": "0.00000500000", "rate": "0.0248602%", "rate1": "0.0248602"}, {"name": "USDT-0626", "mark": 0.9994, "spot_price": 0.9993, "diff": "0.000100000", "rate": "0.0100070%", "rate1": "0.0100070"}, {"name": "LINK-0626", "mark": 4.349, "spot_price": 4.349, "diff": "0E-48", "rate": "0%", "rate1": "0"}]