[{"name": "BAL-0925", "mark": 8.0275, "spot_price": 8.77, "diff": "0.742500", "rate": "8.46636%", "rate1": "8.46636"}, {"name": "COMP-0925", "mark": 155.0, "spot_price": 166.0, "diff": "11", "rate": "6.62651%", "rate1": "6.62651"}, {"name": "TRYB-0925", "mark": 0.14131, "spot_price": 0.14537, "diff": "0.00406000", "rate": "2.79287%", "rate1": "2.79287"}, {"name": "BTC-1225", "mark": 9443.0, "spot_price": 9232.0, "diff": "211", "rate": "2.28553%", "rate1": "2.28553"}, {"name": "SXP-0925", "mark": 0.615, "spot_price": 0.6025, "diff": "0.0125000", "rate": "2.07469%", "rate1": "2.07469"}, {"name": "BCH-0925", "mark": 235.6, "spot_price": 231.0, "diff": "4.60000", "rate": "1.99134%", "rate1": "1.99134"}, {"name": "BTMX-0925", "mark": 0.03676, "spot_price": 0.03733, "diff": "0.000570000", "rate": "1.52692%", "rate1": "1.52692"}, {"name": "ETH-0925", "mark": 243.0, "spot_price": 239.6, "diff": "3.40000", "rate": "1.41903%", "rate1": "1.41903"}, {"name": "BTC-0925", "mark": 9346.0, "spot_price": 9232.0, "diff": "114", "rate": "1.23484%", "rate1": "1.23484"}, {"name": "PAXG-0925", "mark": 1822.4, "spot_price": 1801.0, "diff": "21.4000", "rate": "1.18823%", "rate1": "1.18823"}, {"name": "TRX-0925", "mark": 0.017635, "spot_price": 0.017435, "diff": "0.000200000", "rate": "1.14712%", "rate1": "1.14712"}, {"name": "CUSDT-0925", "mark": 0.020375, "spot_price": 0.020145, "diff": "0.000230000", "rate": "1.14172%", "rate1": "1.14172"}, {"name": "LINK-0925", "mark": 7.4425, "spot_price": 7.3625, "diff": "0.0800000", "rate": "1.08659%", "rate1": "1.08659"}, {"name": "LTC-0925", "mark": 44.26, "spot_price": 43.8, "diff": "0.460000", "rate": "1.05023%", "rate1": "1.05023"}, {"name": "KNC-0925", "mark": 1.4911, "spot_price": 1.4823, "diff": "0.00880000", "rate": "0.593672%", "rate1": "0.593672"}, {"name": "XAUT-0925", "mark": 1797.0, "spot_price": 1798.7, "diff": "1.70000", "rate": "0.0945127%", "rate1": "0.0945127"}, {"name": "BNB-0925", "mark": 18.64, "spot_price": 18.657, "diff": "0.0170000", "rate": "0.0911186%", "rate1": "0.0911186"}, {"name": "USDT-0925", "mark": 0.9996, "spot_price": 0.9993, "diff": "0.000300000", "rate": "0.0300210%", "rate1": "0.0300210"}, {"name": "MKR-0925", "mark": 448.0, "spot_price": 448.0, "diff": "0", "rate": "0%", "rate1": "0"}]