[{"name": "COMP-0925", "mark": 167.6, "spot_price": 259.075, "diff": "91.4750", "rate": "35.3083%", "rate1": "35.3083"}, {"name": "BTMX-0925", "mark": 0.0362, "spot_price": 0.03713, "diff": "0.000930000", "rate": "2.50471%", "rate1": "2.50471"}, {"name": "TRYB-0925", "mark": 0.14075, "spot_price": 0.14384, "diff": "0.00309000", "rate": "2.14822%", "rate1": "2.14822"}, {"name": "BAL-0925", "mark": 12.43, "spot_price": 14.37, "diff": "1.94000", "rate": "13.5003%", "rate1": "13.5003"}, {"name": "CUSDT-0925", "mark": 0.02043, "spot_price": 0.02008, "diff": "0.000350000", "rate": "1.74303%", "rate1": "1.74303"}, {"name": "BTC-1225", "mark": 9306.5, "spot_price": 9157.5, "diff": "149.0", "rate": "1.62708%", "rate1": "1.62708"}, {"name": "KNC-0925", "mark": 1.1484, "spot_price": 1.1612, "diff": "0.0128000", "rate": "1.10231%", "rate1": "1.10231"}, {"name": "TRX-0925", "mark": 0.015945, "spot_price": 0.015785, "diff": "0.000160000", "rate": "1.01362%", "rate1": "1.01362"}, {"name": "ETH-0925", "mark": 232.01, "spot_price": 229.76, "diff": "2.25000", "rate": "0.979283%", "rate1": "0.979283"}, {"name": "BCH-0925", "mark": 232.35, "spot_price": 230.375, "diff": "1.97500", "rate": "0.857298%", "rate1": "0.857298"}, {"name": "BTC-0925", "mark": 9235.0, "spot_price": 9157.5, "diff": "77.5", "rate": "0.846301%", "rate1": "0.846301"}, {"name": "LTC-0925", "mark": 43.41, "spot_price": 43.15, "diff": "0.260000", "rate": "0.602549%", "rate1": "0.602549"}, {"name": "PAXG-0925", "mark": 1780.7, "spot_price": 1770.1, "diff": "10.6000", "rate": "0.598836%", "rate1": "0.598836"}, {"name": "BNB-0925", "mark": 15.6375, "spot_price": 15.701, "diff": "0.0635000", "rate": "0.404433%", "rate1": "0.404433"}, {"name": "XAUT-0925", "mark": 1767.8, "spot_price": 1773.5, "diff": "5.70000", "rate": "0.321398%", "rate1": "0.321398"}, {"name": "LINK-0925", "mark": 4.7325, "spot_price": 4.723, "diff": "0.00950000", "rate": "0.201143%", "rate1": "0.201143"}, {"name": "USDT-0925", "mark": 0.9993, "spot_price": 0.9992, "diff": "0.000100000", "rate": "0.0100080%", "rate1": "0.0100080"}]