[{"name": "BAL-0925", "mark": 7.6, "spot_price": 8.15, "diff": "0.550000", "rate": "6.74847%", "rate1": "6.74847"}, {"name": "COMP-0925", "mark": 157.25, "spot_price": 166.875, "diff": "9.625", "rate": "5.76779%", "rate1": "5.76779"}, {"name": "DMG-0925", "mark": 1.357, "spot_price": 1.285, "diff": "0.0720000", "rate": "5.60311%", "rate1": "5.60311"}, {"name": "BTMX-0925", "mark": 0.03581, "spot_price": 0.03669, "diff": "0.000880000", "rate": "2.39847%", "rate1": "2.39847"}, {"name": "BTC-1225", "mark": 9359.0, "spot_price": 9144.0, "diff": "215", "rate": "2.35127%", "rate1": "2.35127"}, {"name": "SXP-0925", "mark": 1.0045, "spot_price": 0.983, "diff": "0.0215000", "rate": "2.18718%", "rate1": "2.18718"}, {"name": "BCH-0925", "mark": 226.3, "spot_price": 222.225, "diff": "4.07500", "rate": "1.83373%", "rate1": "1.83373"}, {"name": "TRYB-0925", "mark": 0.14193, "spot_price": 0.14401, "diff": "0.00208000", "rate": "1.44434%", "rate1": "1.44434"}, {"name": "ETH-0925", "mark": 235.5, "spot_price": 232.52, "diff": "2.98000", "rate": "1.28161%", "rate1": "1.28161"}, {"name": "CUSDT-0925", "mark": 0.02037, "spot_price": 0.020135, "diff": "0.000235000", "rate": "1.16712%", "rate1": "1.16712"}, {"name": "PAXG-0925", "mark": 1831.1, "spot_price": 1812.1, "diff": "19.0000", "rate": "1.04851%", "rate1": "1.04851"}, {"name": "BTC-0925", "mark": 9236.0, "spot_price": 9144.0, "diff": "92", "rate": "1.00612%", "rate1": "1.00612"}, {"name": "TRX-0925", "mark": 0.0173025, "spot_price": 0.017145, "diff": "0.000157500", "rate": "0.918635%", "rate1": "0.918635"}, {"name": "LINK-0925", "mark": 7.8695, "spot_price": 7.936, "diff": "0.0665000", "rate": "0.837954%", "rate1": "0.837954"}, {"name": "LTC-0925", "mark": 42.1, "spot_price": 41.785, "diff": "0.315000", "rate": "0.753859%", "rate1": "0.753859"}, {"name": "MKR-0925", "mark": 447.0, "spot_price": 450.0, "diff": "3", "rate": "0.666667%", "rate1": "0.666667"}, {"name": "XAUT-0925", "mark": 1800.2, "spot_price": 1803.8, "diff": "3.60000", "rate": "0.199579%", "rate1": "0.199579"}, {"name": "KNC-0925", "mark": 1.7134, "spot_price": 1.7166, "diff": "0.00320000", "rate": "0.186415%", "rate1": "0.186415"}, {"name": "BNB-0925", "mark": 17.07, "spot_price": 17.081, "diff": "0.0110000", "rate": "0.0643990%", "rate1": "0.0643990"}, {"name": "USDT-0925", "mark": 0.9993, "spot_price": 0.9998, "diff": "0.000500000", "rate": "0.0500100%", "rate1": "0.0500100"}]