[{"name": "BTMX-0925", "mark": 0.035, "spot_price": 0.03621, "diff": "0.00121000", "rate": "3.34162%", "rate1": "3.34162"}, {"name": "COMP-0925", "mark": 152.75, "spot_price": 204.65, "diff": "51.9000", "rate": "25.3604%", "rate1": "25.3604"}, {"name": "TRYB-0925", "mark": 0.14025, "spot_price": 0.14423, "diff": "0.00398000", "rate": "2.75948%", "rate1": "2.75948"}, {"name": "BAL-0925", "mark": 9.0175, "spot_price": 10.92, "diff": "1.90250", "rate": "17.4222%", "rate1": "17.4222"}, {"name": "KNC-0925", "mark": 1.4614, "spot_price": 1.6274, "diff": "0.166000", "rate": "10.2003%", "rate1": "10.2003"}, {"name": "BTC-1225", "mark": 9211.0, "spot_price": 9047.5, "diff": "163.5", "rate": "1.80713%", "rate1": "1.80713"}, {"name": "MKR-0925", "mark": 454.0, "spot_price": 460.0, "diff": "6", "rate": "1.30435%", "rate1": "1.30435"}, {"name": "CUSDT-0925", "mark": 0.0203825, "spot_price": 0.020125, "diff": "0.000257500", "rate": "1.27950%", "rate1": "1.27950"}, {"name": "PAXG-0925", "mark": 1791.2, "spot_price": 1774.8, "diff": "16.4000", "rate": "0.924048%", "rate1": "0.924048"}, {"name": "BTC-0925", "mark": 9116.5, "spot_price": 9047.5, "diff": "69.0", "rate": "0.762642%", "rate1": "0.762642"}, {"name": "ETH-0925", "mark": 227.24, "spot_price": 225.59, "diff": "1.65000", "rate": "0.731415%", "rate1": "0.731415"}, {"name": "BCH-0925", "mark": 222.25, "spot_price": 220.825, "diff": "1.42500", "rate": "0.645307%", "rate1": "0.645307"}, {"name": "XAUT-0925", "mark": 1777.9, "spot_price": 1788.1, "diff": "10.2000", "rate": "0.570438%", "rate1": "0.570438"}, {"name": "TRX-0925", "mark": 0.0166475, "spot_price": 0.0165775, "diff": "0.0000700000", "rate": "0.422259%", "rate1": "0.422259"}, {"name": "LTC-0925", "mark": 41.56, "spot_price": 41.435, "diff": "0.125000", "rate": "0.301677%", "rate1": "0.301677"}, {"name": "BNB-0925", "mark": 15.42, "spot_price": 15.405, "diff": "0.0150000", "rate": "0.0973710%", "rate1": "0.0973710"}, {"name": "USDT-0925", "mark": 0.9993, "spot_price": 0.9998, "diff": "0.000500000", "rate": "0.0500100%", "rate1": "0.0500100"}, {"name": "LINK-0925", "mark": 4.687, "spot_price": 4.689, "diff": "0.00200000", "rate": "0.0426530%", "rate1": "0.0426530"}]