[{"name": "BAL-0925", "mark": 9.67, "spot_price": 10.4775, "diff": "0.807500", "rate": "7.70699%", "rate1": "7.70699"}, {"name": "RUNE-0925", "mark": 0.4935, "spot_price": 0.463, "diff": "0.0305000", "rate": "6.58747%", "rate1": "6.58747"}, {"name": "COMP-0925", "mark": 123.5, "spot_price": 130.8, "diff": "7.30000", "rate": "5.58104%", "rate1": "5.58104"}, {"name": "DMG-0925", "mark": 1.195, "spot_price": 1.132, "diff": "0.0630000", "rate": "5.56537%", "rate1": "5.56537"}, {"name": "ETH-0925", "mark": 400.23, "spot_price": 385.77, "diff": "14.4600", "rate": "3.74835%", "rate1": "3.74835"}, {"name": "BTC-1225", "mark": 11550.0, "spot_price": 11134.0, "diff": "416", "rate": "3.73630%", "rate1": "3.73630"}, {"name": "TRX-0925", "mark": 0.02071, "spot_price": 0.0201775, "diff": "0.000532500", "rate": "2.63908%", "rate1": "2.63908"}, {"name": "BCH-0925", "mark": 293.1, "spot_price": 285.875, "diff": "7.22500", "rate": "2.52733%", "rate1": "2.52733"}, {"name": "SXP-0925", "mark": 2.1, "spot_price": 2.0515, "diff": "0.0485000", "rate": "2.36412%", "rate1": "2.36412"}, {"name": "BTC-0925", "mark": 11394.5, "spot_price": 11134.0, "diff": "260.5", "rate": "2.33968%", "rate1": "2.33968"}, {"name": "LTC-0925", "mark": 58.81, "spot_price": 57.47, "diff": "1.34000", "rate": "2.33165%", "rate1": "2.33165"}, {"name": "MTA-0925", "mark": 4.6785, "spot_price": 5.627, "diff": "0.948500", "rate": "16.8562%", "rate1": "16.8562"}, {"name": "SOL-0925", "mark": 1.8775, "spot_price": 1.8425, "diff": "0.0350000", "rate": "1.89959%", "rate1": "1.89959"}, {"name": "PAXG-0925", "mark": 2020.0, "spot_price": 1986.5, "diff": "33.5", "rate": "1.68638%", "rate1": "1.68638"}, {"name": "XRP-0925", "mark": 0.3019, "spot_price": 0.29715, "diff": "0.00475000", "rate": "1.59852%", "rate1": "1.59852"}, {"name": "BTMX-0925", "mark": 0.06684, "spot_price": 0.06755, "diff": "0.000710000", "rate": "1.05107%", "rate1": "1.05107"}, {"name": "CUSDT-0925", "mark": 0.020385, "spot_price": 0.0201975, "diff": "0.000187500", "rate": "0.928333%", "rate1": "0.928333"}, {"name": "TRYB-0925", "mark": 0.14027, "spot_price": 0.14143, "diff": "0.00116000", "rate": "0.820194%", "rate1": "0.820194"}, {"name": "MKR-0925", "mark": 584.5, "spot_price": 588.5, "diff": "4.0", "rate": "0.679694%", "rate1": "0.679694"}, {"name": "KNC-0925", "mark": 1.4351, "spot_price": 1.4255, "diff": "0.00960000", "rate": "0.673448%", "rate1": "0.673448"}, {"name": "XAUT-0925", "mark": 1973.6, "spot_price": 1963.4, "diff": "10.2000", "rate": "0.519507%", "rate1": "0.519507"}, {"name": "BNB-0925", "mark": 21.9275, "spot_price": 21.859, "diff": "0.0685000", "rate": "0.313372%", "rate1": "0.313372"}, {"name": "LINK-0925", "mark": 9.4615, "spot_price": 9.4745, "diff": "0.0130000", "rate": "0.137210%", "rate1": "0.137210"}, {"name": "USDT-0925", "mark": 0.9997, "spot_price": 1.0003, "diff": "0.000600000", "rate": "0.0599820%", "rate1": "0.0599820"}]