[{"name": "BAL-0925", "mark": 8.22, "spot_price": 9.1, "diff": "0.880000", "rate": "9.67033%", "rate1": "9.67033"}, {"name": "COMP-0925", "mark": 126.5, "spot_price": 134.7, "diff": "8.20000", "rate": "6.08760%", "rate1": "6.08760"}, {"name": "MTA-0925", "mark": 5.53, "spot_price": 5.846, "diff": "0.316000", "rate": "5.40541%", "rate1": "5.40541"}, {"name": "BTC-1225", "mark": 11596.5, "spot_price": 11027.0, "diff": "569.5", "rate": "5.16460%", "rate1": "5.16460"}, {"name": "DMG-0925", "mark": 1.171, "spot_price": 1.119, "diff": "0.0520000", "rate": "4.64701%", "rate1": "4.64701"}, {"name": "RUNE-0925", "mark": 0.49, "spot_price": 0.4725, "diff": "0.0175000", "rate": "3.70370%", "rate1": "3.70370"}, {"name": "BTMX-0925", "mark": 0.04827, "spot_price": 0.05005, "diff": "0.00178000", "rate": "3.55644%", "rate1": "3.55644"}, {"name": "BCH-0925", "mark": 298.1, "spot_price": 289.5, "diff": "8.60000", "rate": "2.97064%", "rate1": "2.97064"}, {"name": "ETH-0925", "mark": 331.77, "spot_price": 322.41, "diff": "9.36000", "rate": "2.90314%", "rate1": "2.90314"}, {"name": "LTC-0925", "mark": 57.07, "spot_price": 55.605, "diff": "1.46500", "rate": "2.63466%", "rate1": "2.63466"}, {"name": "BTC-0925", "mark": 11315.5, "spot_price": 11027.0, "diff": "288.5", "rate": "2.61631%", "rate1": "2.61631"}, {"name": "SOL-0925", "mark": 1.75, "spot_price": 1.7125, "diff": "0.0375000", "rate": "2.18978%", "rate1": "2.18978"}, {"name": "TRX-0925", "mark": 0.01996, "spot_price": 0.01954, "diff": "0.000420000", "rate": "2.14944%", "rate1": "2.14944"}, {"name": "SXP-0925", "mark": 1.595, "spot_price": 1.569, "diff": "0.0260000", "rate": "1.65711%", "rate1": "1.65711"}, {"name": "TRYB-0925", "mark": 0.14125, "spot_price": 0.14352, "diff": "0.00227000", "rate": "1.58166%", "rate1": "1.58166"}, {"name": "XRP-0925", "mark": 0.2428, "spot_price": 0.23935, "diff": "0.00345000", "rate": "1.44140%", "rate1": "1.44140"}, {"name": "XAUT-0925", "mark": 1935.5, "spot_price": 1917.2, "diff": "18.3000", "rate": "0.954517%", "rate1": "0.954517"}, {"name": "PAXG-0925", "mark": 1979.8, "spot_price": 1961.7, "diff": "18.1000", "rate": "0.922669%", "rate1": "0.922669"}, {"name": "CUSDT-0925", "mark": 0.02037, "spot_price": 0.0202275, "diff": "0.000142500", "rate": "0.704486%", "rate1": "0.704486"}, {"name": "BNB-0925", "mark": 20.0, "spot_price": 20.075, "diff": "0.0750000", "rate": "0.373599%", "rate1": "0.373599"}, {"name": "KNC-0925", "mark": 1.4651, "spot_price": 1.46, "diff": "0.00510000", "rate": "0.349315%", "rate1": "0.349315"}, {"name": "LINK-0925", "mark": 7.2265, "spot_price": 7.205, "diff": "0.0215000", "rate": "0.298404%", "rate1": "0.298404"}, {"name": "USDT-0925", "mark": 0.9994, "spot_price": 1.001, "diff": "0.00160000", "rate": "0.159840%", "rate1": "0.159840"}, {"name": "MKR-0925", "mark": 526.5, "spot_price": 526.0, "diff": "0.5", "rate": "0.0950570%", "rate1": "0.0950570"}]