[{"name": "DMG-0925", "mark": 1.165, "spot_price": 1.103, "diff": "0.0620000", "rate": "5.62103%", "rate1": "5.62103"}, {"name": "BTMX-0925", "mark": 0.0467, "spot_price": 0.04939, "diff": "0.00269000", "rate": "5.44645%", "rate1": "5.44645"}, {"name": "RUNE-0925", "mark": 0.4995, "spot_price": 0.476, "diff": "0.0235000", "rate": "4.93697%", "rate1": "4.93697"}, {"name": "BTC-1225", "mark": 10468.0, "spot_price": 10048.5, "diff": "419.5", "rate": "4.17475%", "rate1": "4.17475"}, {"name": "BAL-0925", "mark": 10.505, "spot_price": 10.8725, "diff": "0.367500", "rate": "3.38009%", "rate1": "3.38009"}, {"name": "SXP-0925", "mark": 1.788, "spot_price": 1.733, "diff": "0.0550000", "rate": "3.17369%", "rate1": "3.17369"}, {"name": "COMP-0925", "mark": 151.0, "spot_price": 155.7, "diff": "4.70000", "rate": "3.01863%", "rate1": "3.01863"}, {"name": "BTC-0925", "mark": 10275.0, "spot_price": 10048.5, "diff": "226.5", "rate": "2.25407%", "rate1": "2.25407"}, {"name": "BCH-0925", "mark": 256.6, "spot_price": 251.3, "diff": "5.30000", "rate": "2.10903%", "rate1": "2.10903"}, {"name": "ETH-0925", "mark": 328.99, "spot_price": 322.21, "diff": "6.78000", "rate": "2.10422%", "rate1": "2.10422"}, {"name": "TRYB-0925", "mark": 0.14315, "spot_price": 0.14612, "diff": "0.00297000", "rate": "2.03258%", "rate1": "2.03258"}, {"name": "LTC-0925", "mark": 49.7, "spot_price": 48.8, "diff": "0.900000", "rate": "1.84426%", "rate1": "1.84426"}, {"name": "MTA-0925", "mark": 5.279, "spot_price": 5.3695, "diff": "0.0905000", "rate": "1.68545%", "rate1": "1.68545"}, {"name": "SOL-0925", "mark": 1.785, "spot_price": 1.76, "diff": "0.0250000", "rate": "1.42045%", "rate1": "1.42045"}, {"name": "BNB-0925", "mark": 19.115, "spot_price": 19.36, "diff": "0.245000", "rate": "1.26550%", "rate1": "1.26550"}, {"name": "KNC-0925", "mark": 1.4878, "spot_price": 1.4708, "diff": "0.0170000", "rate": "1.15583%", "rate1": "1.15583"}, {"name": "TRX-0925", "mark": 0.01904, "spot_price": 0.01883, "diff": "0.000210000", "rate": "1.11524%", "rate1": "1.11524"}, {"name": "PAXG-0925", "mark": 1945.4, "spot_price": 1924.5, "diff": "20.9000", "rate": "1.08600%", "rate1": "1.08600"}, {"name": "CUSDT-0925", "mark": 0.020375, "spot_price": 0.02018, "diff": "0.000195000", "rate": "0.966303%", "rate1": "0.966303"}, {"name": "XRP-0925", "mark": 0.220175, "spot_price": 0.218525, "diff": "0.00165000", "rate": "0.755062%", "rate1": "0.755062"}, {"name": "LINK-0925", "mark": 7.3815, "spot_price": 7.331, "diff": "0.0505000", "rate": "0.688856%", "rate1": "0.688856"}, {"name": "MKR-0925", "mark": 525.0, "spot_price": 524.0, "diff": "1", "rate": "0.190840%", "rate1": "0.190840"}, {"name": "USDT-0925", "mark": 0.9994, "spot_price": 1.0008, "diff": "0.00140000", "rate": "0.139888%", "rate1": "0.139888"}, {"name": "XAUT-0925", "mark": 1900.5, "spot_price": 1898.2, "diff": "2.30000", "rate": "0.121167%", "rate1": "0.121167"}]