[{"name": "BAL-0925", "mark": 8.7325, "spot_price": 9.6025, "diff": "0.870000", "rate": "9.06014%", "rate1": "9.06014"}, {"name": "RUNE-0925", "mark": 0.5555, "spot_price": 0.5235, "diff": "0.0320000", "rate": "6.11270%", "rate1": "6.11270"}, {"name": "COMP-0925", "mark": 124.5, "spot_price": 132.3, "diff": "7.80000", "rate": "5.89569%", "rate1": "5.89569"}, {"name": "MTA-0925", "mark": 6.012, "spot_price": 6.3295, "diff": "0.317500", "rate": "5.01619%", "rate1": "5.01619"}, {"name": "BTC-1225", "mark": 11597.0, "spot_price": 11088.0, "diff": "509", "rate": "4.59055%", "rate1": "4.59055"}, {"name": "DMG-0925", "mark": 1.159, "spot_price": 1.113, "diff": "0.0460000", "rate": "4.13297%", "rate1": "4.13297"}, {"name": "BTMX-0925", "mark": 0.04828, "spot_price": 0.05021, "diff": "0.00193000", "rate": "3.84386%", "rate1": "3.84386"}, {"name": "BCH-0925", "mark": 293.25, "spot_price": 285.5, "diff": "7.75", "rate": "2.71454%", "rate1": "2.71454"}, {"name": "SOL-0925", "mark": 1.7175, "spot_price": 1.6725, "diff": "0.0450000", "rate": "2.69058%", "rate1": "2.69058"}, {"name": "ETH-0925", "mark": 327.28, "spot_price": 318.91, "diff": "8.37000", "rate": "2.62456%", "rate1": "2.62456"}, {"name": "LTC-0925", "mark": 56.64, "spot_price": 55.28, "diff": "1.36000", "rate": "2.46020%", "rate1": "2.46020"}, {"name": "BTC-0925", "mark": 11327.0, "spot_price": 11088.0, "diff": "239", "rate": "2.15548%", "rate1": "2.15548"}, {"name": "TRX-0925", "mark": 0.0194975, "spot_price": 0.0191175, "diff": "0.000380000", "rate": "1.98771%", "rate1": "1.98771"}, {"name": "XAUT-0925", "mark": 1965.4, "spot_price": 1930.5, "diff": "34.9000", "rate": "1.80782%", "rate1": "1.80782"}, {"name": "SXP-0925", "mark": 1.5955, "spot_price": 1.5685, "diff": "0.0270000", "rate": "1.72139%", "rate1": "1.72139"}, {"name": "TRYB-0925", "mark": 0.14078, "spot_price": 0.14282, "diff": "0.00204000", "rate": "1.42837%", "rate1": "1.42837"}, {"name": "XRP-0925", "mark": 0.24415, "spot_price": 0.241275, "diff": "0.00287500", "rate": "1.19159%", "rate1": "1.19159"}, {"name": "PAXG-0925", "mark": 1990.9, "spot_price": 1969.4, "diff": "21.5000", "rate": "1.09170%", "rate1": "1.09170"}, {"name": "CUSDT-0925", "mark": 0.02037, "spot_price": 0.020175, "diff": "0.000195000", "rate": "0.966543%", "rate1": "0.966543"}, {"name": "KNC-0925", "mark": 1.4571, "spot_price": 1.4467, "diff": "0.0104000", "rate": "0.718877%", "rate1": "0.718877"}, {"name": "MKR-0925", "mark": 540.5, "spot_price": 539.0, "diff": "1.5", "rate": "0.278293%", "rate1": "0.278293"}, {"name": "LINK-0925", "mark": 7.1625, "spot_price": 7.175, "diff": "0.0125000", "rate": "0.174216%", "rate1": "0.174216"}, {"name": "BNB-0925", "mark": 19.9725, "spot_price": 19.939, "diff": "0.0335000", "rate": "0.168012%", "rate1": "0.168012"}, {"name": "USDT-0925", "mark": 0.9994, "spot_price": 1.0008, "diff": "0.00140000", "rate": "0.139888%", "rate1": "0.139888"}]