[{"name": "MTA-0925", "mark": 4.862, "spot_price": 5.272, "diff": "0.410000", "rate": "7.77693%", "rate1": "7.77693"}, {"name": "COMP-0925", "mark": 126.75, "spot_price": 135.0, "diff": "8.25", "rate": "6.11111%", "rate1": "6.11111"}, {"name": "RUNE-0925", "mark": 0.4885, "spot_price": 0.4605, "diff": "0.0280000", "rate": "6.08035%", "rate1": "6.08035"}, {"name": "DMG-0925", "mark": 1.101, "spot_price": 1.054, "diff": "0.0470000", "rate": "4.45920%", "rate1": "4.45920"}, {"name": "BTC-1225", "mark": 11719.0, "spot_price": 11265.0, "diff": "454", "rate": "4.03018%", "rate1": "4.03018"}, {"name": "BAL-0925", "mark": 10.13, "spot_price": 10.52, "diff": "0.390000", "rate": "3.70722%", "rate1": "3.70722"}, {"name": "BTMX-0925", "mark": 0.04883, "spot_price": 0.05039, "diff": "0.00156000", "rate": "3.09585%", "rate1": "3.09585"}, {"name": "SXP-0925", "mark": 1.861, "spot_price": 1.8075, "diff": "0.0535000", "rate": "2.95989%", "rate1": "2.95989"}, {"name": "BCH-0925", "mark": 307.9, "spot_price": 299.15, "diff": "8.75000", "rate": "2.92495%", "rate1": "2.92495"}, {"name": "LTC-0925", "mark": 59.42, "spot_price": 57.74, "diff": "1.68000", "rate": "2.90959%", "rate1": "2.90959"}, {"name": "ETH-0925", "mark": 353.83, "spot_price": 344.43, "diff": "9.40000", "rate": "2.72915%", "rate1": "2.72915"}, {"name": "SOL-0925", "mark": 1.555, "spot_price": 1.515, "diff": "0.0400000", "rate": "2.64026%", "rate1": "2.64026"}, {"name": "TRX-0925", "mark": 0.0200975, "spot_price": 0.0195975, "diff": "0.000500000", "rate": "2.55135%", "rate1": "2.55135"}, {"name": "BTC-0925", "mark": 11505.0, "spot_price": 11265.0, "diff": "240", "rate": "2.13049%", "rate1": "2.13049"}, {"name": "PAXG-0925", "mark": 2012.0, "spot_price": 1979.5, "diff": "32.5", "rate": "1.64183%", "rate1": "1.64183"}, {"name": "TRYB-0925", "mark": 0.13936, "spot_price": 0.14137, "diff": "0.00201000", "rate": "1.42180%", "rate1": "1.42180"}, {"name": "XRP-0925", "mark": 0.25985, "spot_price": 0.256825, "diff": "0.00302500", "rate": "1.17784%", "rate1": "1.17784"}, {"name": "CUSDT-0925", "mark": 0.0203775, "spot_price": 0.020195, "diff": "0.000182500", "rate": "0.903689%", "rate1": "0.903689"}, {"name": "KNC-0925", "mark": 1.4689, "spot_price": 1.4573, "diff": "0.0116000", "rate": "0.795993%", "rate1": "0.795993"}, {"name": "XAUT-0925", "mark": 1965.2, "spot_price": 1952.7, "diff": "12.5000", "rate": "0.640139%", "rate1": "0.640139"}, {"name": "LINK-0925", "mark": 7.7265, "spot_price": 7.752, "diff": "0.0255000", "rate": "0.328947%", "rate1": "0.328947"}, {"name": "BNB-0925", "mark": 20.6625, "spot_price": 20.625, "diff": "0.0375000", "rate": "0.181818%", "rate1": "0.181818"}, {"name": "MKR-0925", "mark": 552.5, "spot_price": 553.5, "diff": "1.0", "rate": "0.180668%", "rate1": "0.180668"}, {"name": "USDT-0925", "mark": 0.9999, "spot_price": 1.0012, "diff": "0.00130000", "rate": "0.129844%", "rate1": "0.129844"}]