[{"name": "BTMX-0925", "mark": 0.04659, "spot_price": 0.04915, "diff": "0.00256000", "rate": "5.20855%", "rate1": "5.20855"}, {"name": "DMG-0925", "mark": 1.176, "spot_price": 1.118, "diff": "0.0580000", "rate": "5.18784%", "rate1": "5.18784"}, {"name": "COMP-0925", "mark": 155.0, "spot_price": 161.475, "diff": "6.47500", "rate": "4.00991%", "rate1": "4.00991"}, {"name": "BAL-0925", "mark": 10.4925, "spot_price": 10.86, "diff": "0.367500", "rate": "3.38398%", "rate1": "3.38398"}, {"name": "BTC-1225", "mark": 9995.0, "spot_price": 9678.0, "diff": "317", "rate": "3.27547%", "rate1": "3.27547"}, {"name": "SXP-0925", "mark": 2.03, "spot_price": 1.9675, "diff": "0.0625000", "rate": "3.17662%", "rate1": "3.17662"}, {"name": "RUNE-0925", "mark": 0.6425, "spot_price": 0.6235, "diff": "0.0190000", "rate": "3.04731%", "rate1": "3.04731"}, {"name": "LTC-0925", "mark": 49.57, "spot_price": 48.545, "diff": "1.02500", "rate": "2.11144%", "rate1": "2.11144"}, {"name": "TRYB-0925", "mark": 0.14315, "spot_price": 0.14615, "diff": "0.00300000", "rate": "2.05269%", "rate1": "2.05269"}, {"name": "ETH-0925", "mark": 308.44, "spot_price": 302.71, "diff": "5.73000", "rate": "1.89290%", "rate1": "1.89290"}, {"name": "BNB-0925", "mark": 20.04, "spot_price": 19.669, "diff": "0.371000", "rate": "1.88622%", "rate1": "1.88622"}, {"name": "BCH-0925", "mark": 254.4, "spot_price": 250.1, "diff": "4.30000", "rate": "1.71931%", "rate1": "1.71931"}, {"name": "BTC-0925", "mark": 9830.0, "spot_price": 9678.0, "diff": "152", "rate": "1.57057%", "rate1": "1.57057"}, {"name": "TRX-0925", "mark": 0.019175, "spot_price": 0.0189075, "diff": "0.000267500", "rate": "1.41478%", "rate1": "1.41478"}, {"name": "PAXG-0925", "mark": 1927.0, "spot_price": 1907.7, "diff": "19.3000", "rate": "1.01169%", "rate1": "1.01169"}, {"name": "CUSDT-0925", "mark": 0.0203825, "spot_price": 0.0202, "diff": "0.000182500", "rate": "0.903465%", "rate1": "0.903465"}, {"name": "LINK-0925", "mark": 7.9415, "spot_price": 7.879, "diff": "0.0625000", "rate": "0.793248%", "rate1": "0.793248"}, {"name": "XRP-0925", "mark": 0.22065, "spot_price": 0.2196, "diff": "0.00105000", "rate": "0.478142%", "rate1": "0.478142"}, {"name": "KNC-0925", "mark": 1.5819, "spot_price": 1.5755, "diff": "0.00640000", "rate": "0.406220%", "rate1": "0.406220"}, {"name": "XAUT-0925", "mark": 1891.8, "spot_price": 1886.1, "diff": "5.70000", "rate": "0.302211%", "rate1": "0.302211"}, {"name": "MKR-0925", "mark": 535.0, "spot_price": 534.0, "diff": "1", "rate": "0.187266%", "rate1": "0.187266"}, {"name": "USDT-0925", "mark": 0.9994, "spot_price": 1.0009, "diff": "0.00150000", "rate": "0.149865%", "rate1": "0.149865"}]