[{"name": "COMP-0925", "mark": 161.75, "spot_price": 174.575, "diff": "12.8250", "rate": "7.34641%", "rate1": "7.34641"}, {"name": "BAL-0925", "mark": 8.9725, "spot_price": 9.605, "diff": "0.632500", "rate": "6.58511%", "rate1": "6.58511"}, {"name": "TRYB-0925", "mark": 0.14117, "spot_price": 0.14532, "diff": "0.00415000", "rate": "2.85577%", "rate1": "2.85577"}, {"name": "BTC-1225", "mark": 9500.0, "spot_price": 9278.0, "diff": "222", "rate": "2.39276%", "rate1": "2.39276"}, {"name": "BTMX-0925", "mark": 0.03656, "spot_price": 0.03737, "diff": "0.000810000", "rate": "2.16751%", "rate1": "2.16751"}, {"name": "SXP-0925", "mark": 0.5715, "spot_price": 0.56, "diff": "0.0115000", "rate": "2.05357%", "rate1": "2.05357"}, {"name": "BCH-0925", "mark": 241.2, "spot_price": 236.825, "diff": "4.37500", "rate": "1.84736%", "rate1": "1.84736"}, {"name": "ETH-0925", "mark": 247.58, "spot_price": 243.79, "diff": "3.79000", "rate": "1.55462%", "rate1": "1.55462"}, {"name": "BTC-0925", "mark": 9400.0, "spot_price": 9278.0, "diff": "122", "rate": "1.31494%", "rate1": "1.31494"}, {"name": "PAXG-0925", "mark": 1832.5, "spot_price": 1809.5, "diff": "23.0", "rate": "1.27107%", "rate1": "1.27107"}, {"name": "TRX-0925", "mark": 0.018555, "spot_price": 0.0183225, "diff": "0.000232500", "rate": "1.26893%", "rate1": "1.26893"}, {"name": "LTC-0925", "mark": 45.77, "spot_price": 45.205, "diff": "0.565000", "rate": "1.24986%", "rate1": "1.24986"}, {"name": "CUSDT-0925", "mark": 0.020385, "spot_price": 0.0201675, "diff": "0.000217500", "rate": "1.07847%", "rate1": "1.07847"}, {"name": "LINK-0925", "mark": 7.864, "spot_price": 7.8155, "diff": "0.0485000", "rate": "0.620562%", "rate1": "0.620562"}, {"name": "XAUT-0925", "mark": 1800.0, "spot_price": 1789.5, "diff": "10.5", "rate": "0.586756%", "rate1": "0.586756"}, {"name": "KNC-0925", "mark": 1.6233, "spot_price": 1.6323, "diff": "0.00900000", "rate": "0.551369%", "rate1": "0.551369"}, {"name": "MKR-0925", "mark": 461.0, "spot_price": 462.5, "diff": "1.5", "rate": "0.324324%", "rate1": "0.324324"}, {"name": "USDT-0925", "mark": 0.9996, "spot_price": 0.9999, "diff": "0.000300000", "rate": "0.0300030%", "rate1": "0.0300030"}, {"name": "BNB-0925", "mark": 18.255, "spot_price": 18.255, "diff": "0E-48", "rate": "0%", "rate1": "0"}]