[{"name": "BAL-0925", "mark": 9.8475, "spot_price": 10.4075, "diff": "0.560000", "rate": "5.38074%", "rate1": "5.38074"}, {"name": "COMP-0925", "mark": 150.25, "spot_price": 158.55, "diff": "8.30000", "rate": "5.23494%", "rate1": "5.23494"}, {"name": "RUNE-0925", "mark": 0.5705, "spot_price": 0.543, "diff": "0.0275000", "rate": "5.06446%", "rate1": "5.06446"}, {"name": "DMG-0925", "mark": 1.353, "spot_price": 1.292, "diff": "0.0610000", "rate": "4.72136%", "rate1": "4.72136"}, {"name": "BTC-1225", "mark": 9630.5, "spot_price": 9383.0, "diff": "247.5", "rate": "2.63775%", "rate1": "2.63775"}, {"name": "BTMX-0925", "mark": 0.04318, "spot_price": 0.04433, "diff": "0.00115000", "rate": "2.59418%", "rate1": "2.59418"}, {"name": "SXP-0925", "mark": 1.6875, "spot_price": 1.646, "diff": "0.0415000", "rate": "2.52126%", "rate1": "2.52126"}, {"name": "BCH-0925", "mark": 234.15, "spot_price": 229.65, "diff": "4.50000", "rate": "1.95950%", "rate1": "1.95950"}, {"name": "TRYB-0925", "mark": 0.14276, "spot_price": 0.14484, "diff": "0.00208000", "rate": "1.43607%", "rate1": "1.43607"}, {"name": "ETH-0925", "mark": 248.0, "spot_price": 244.51, "diff": "3.49000", "rate": "1.42734%", "rate1": "1.42734"}, {"name": "BTC-0925", "mark": 9502.0, "spot_price": 9383.0, "diff": "119", "rate": "1.26825%", "rate1": "1.26825"}, {"name": "LTC-0925", "mark": 44.03, "spot_price": 43.5, "diff": "0.530000", "rate": "1.21839%", "rate1": "1.21839"}, {"name": "PAXG-0925", "mark": 1866.5, "spot_price": 1846.2, "diff": "20.3000", "rate": "1.09956%", "rate1": "1.09956"}, {"name": "XAUT-0925", "mark": 1829.8, "spot_price": 1811.7, "diff": "18.1000", "rate": "0.999062%", "rate1": "0.999062"}, {"name": "TRX-0925", "mark": 0.017775, "spot_price": 0.0176025, "diff": "0.000172500", "rate": "0.979974%", "rate1": "0.979974"}, {"name": "MKR-0925", "mark": 461.5, "spot_price": 457.5, "diff": "4.0", "rate": "0.874317%", "rate1": "0.874317"}, {"name": "CUSDT-0925", "mark": 0.0203625, "spot_price": 0.02019, "diff": "0.000172500", "rate": "0.854383%", "rate1": "0.854383"}, {"name": "XRP-0925", "mark": 0.199025, "spot_price": 0.19855, "diff": "0.000475000", "rate": "0.239234%", "rate1": "0.239234"}, {"name": "KNC-0925", "mark": 1.6741, "spot_price": 1.6768, "diff": "0.00270000", "rate": "0.161021%", "rate1": "0.161021"}, {"name": "LINK-0925", "mark": 7.231, "spot_price": 7.224, "diff": "0.00700000", "rate": "0.0968992%", "rate1": "0.0968992"}, {"name": "USDT-0925", "mark": 0.9995, "spot_price": 1.0004, "diff": "0.000900000", "rate": "0.0899640%", "rate1": "0.0899640"}, {"name": "BNB-0925", "mark": 17.685, "spot_price": 17.695, "diff": "0.0100000", "rate": "0.0565131%", "rate1": "0.0565131"}]