[{"name": "COMP-0925", "mark": 163.25, "spot_price": 180.0, "diff": "16.75", "rate": "9.30556%", "rate1": "9.30556"}, {"name": "BTMX-0925", "mark": 0.03585, "spot_price": 0.0371, "diff": "0.00125000", "rate": "3.36927%", "rate1": "3.36927"}, {"name": "KNC-0925", "mark": 1.5601, "spot_price": 1.6127, "diff": "0.0526000", "rate": "3.26161%", "rate1": "3.26161"}, {"name": "TRYB-0925", "mark": 0.14124, "spot_price": 0.14565, "diff": "0.00441000", "rate": "3.02781%", "rate1": "3.02781"}, {"name": "BTC-1225", "mark": 9510.0, "spot_price": 9296.0, "diff": "214", "rate": "2.30207%", "rate1": "2.30207"}, {"name": "BAL-0925", "mark": 8.125, "spot_price": 9.33, "diff": "1.20500", "rate": "12.9153%", "rate1": "12.9153"}, {"name": "ETH-0925", "mark": 245.73, "spot_price": 242.39, "diff": "3.34000", "rate": "1.37794%", "rate1": "1.37794"}, {"name": "CUSDT-0925", "mark": 0.0203975, "spot_price": 0.02013, "diff": "0.000267500", "rate": "1.32886%", "rate1": "1.32886"}, {"name": "BCH-0925", "mark": 242.1, "spot_price": 239.225, "diff": "2.87500", "rate": "1.20180%", "rate1": "1.20180"}, {"name": "PAXG-0925", "mark": 1834.8, "spot_price": 1813.1, "diff": "21.7000", "rate": "1.19685%", "rate1": "1.19685"}, {"name": "BTC-0925", "mark": 9394.0, "spot_price": 9296.0, "diff": "98", "rate": "1.05422%", "rate1": "1.05422"}, {"name": "TRX-0925", "mark": 0.01833, "spot_price": 0.0181525, "diff": "0.000177500", "rate": "0.977827%", "rate1": "0.977827"}, {"name": "MKR-0925", "mark": 456.5, "spot_price": 459.5, "diff": "3.0", "rate": "0.652884%", "rate1": "0.652884"}, {"name": "LTC-0925", "mark": 44.89, "spot_price": 44.625, "diff": "0.265000", "rate": "0.593838%", "rate1": "0.593838"}, {"name": "LINK-0925", "mark": 6.0555, "spot_price": 6.0305, "diff": "0.0250000", "rate": "0.414559%", "rate1": "0.414559"}, {"name": "XAUT-0925", "mark": 1811.1, "spot_price": 1806.7, "diff": "4.40000", "rate": "0.243538%", "rate1": "0.243538"}, {"name": "USDT-0925", "mark": 0.9994, "spot_price": 0.9997, "diff": "0.000300000", "rate": "0.0300090%", "rate1": "0.0300090"}, {"name": "BNB-0925", "mark": 16.77, "spot_price": 16.769, "diff": "0.00100000", "rate": "0.00596338%", "rate1": "0.00596338"}]