[{"nextFundingRate": 0.000499, "nextFundingTime": "2020-07-30T05:00:00+00:00", "name": "RUNE-PERP", "24hrate": "1.19760%"}, {"nextFundingRate": 0.000469, "nextFundingTime": "2020-07-30T05:00:00+00:00", "name": "AMPL-PERP", "24hrate": "1.12560%"}, {"nextFundingRate": 0.000409, "nextFundingTime": "2020-07-30T05:00:00+00:00", "name": "BAL-PERP", "24hrate": "0.981600%"}, {"nextFundingRate": -0.000285, "nextFundingTime": "2020-07-30T05:00:00+00:00", "name": "BTMX-PERP", "24hrate": "-0.684000%"}, {"nextFundingRate": 0.00028, "nextFundingTime": "2020-07-30T05:00:00+00:00", "name": "DMG-PERP", "24hrate": "0.672000%"}, {"nextFundingRate": 0.000246, "nextFundingTime": "2020-07-30T05:00:00+00:00", "name": "DOT-PERP", "24hrate": "0.590400%"}, {"nextFundingRate": 0.000197, "nextFundingTime": "2020-07-30T05:00:00+00:00", "name": "SXP-PERP", "24hrate": "0.472800%"}, {"nextFundingRate": 0.000145, "nextFundingTime": "2020-07-30T05:00:00+00:00", "name": "THETA-PERP", "24hrate": "0.348000%"}, {"nextFundingRate": 0.000128, "nextFundingTime": "2020-07-30T05:00:00+00:00", "name": "TOMO-PERP", "24hrate": "0.307200%"}, {"nextFundingRate": 0.000128, "nextFundingTime": "2020-07-30T05:00:00+00:00", "name": "VET-PERP", "24hrate": "0.307200%"}, {"nextFundingRate": 0.000118, "nextFundingTime": "2020-07-30T05:00:00+00:00", "name": "SOL-PERP", "24hrate": "0.283200%"}, {"nextFundingRate": 0.000116, "nextFundingTime": "2020-07-30T05:00:00+00:00", "name": "MID-PERP", "24hrate": "0.278400%"}, {"nextFundingRate": -0.000114, "nextFundingTime": "2020-07-30T05:00:00+00:00", "name": "TRYB-PERP", "24hrate": "-0.273600%"}, {"nextFundingRate": 9.6e-05, "nextFundingTime": "2020-07-30T05:00:00+00:00", "name": "ATOM-PERP", "24hrate": "0.230400%"}, {"nextFundingRate": 9.5e-05, "nextFundingTime": "2020-07-30T05:00:00+00:00", "name": "LEO-PERP", "24hrate": "0.228000%"}, {"nextFundingRate": -8.8e-05, "nextFundingTime": "2020-07-30T05:00:00+00:00", "name": "MTA-PERP", "24hrate": "-0.211200%"}, {"nextFundingRate": 8.4e-05, "nextFundingTime": "2020-07-30T05:00:00+00:00", "name": "EOS-PERP", "24hrate": "0.201600%"}, {"nextFundingRate": 8.2e-05, "nextFundingTime": "2020-07-30T05:00:00+00:00", "name": "ETC-PERP", "24hrate": "0.196800%"}, {"nextFundingRate": 8.2e-05, "nextFundingTime": "2020-07-30T05:00:00+00:00", "name": "KNC-PERP", "24hrate": "0.196800%"}, {"nextFundingRate": 7.8e-05, "nextFundingTime": "2020-07-30T05:00:00+00:00", "name": "ALGO-PERP", "24hrate": "0.187200%"}]