[{"nextFundingRate": 0.001678, "nextFundingTime": "2020-08-08T14:00:00+00:00", "name": "AMPL-PERP", "24hrate": "4.02720%"}, {"nextFundingRate": -0.000557, "nextFundingTime": "2020-08-08T14:00:00+00:00", "name": "MTA-PERP", "24hrate": "-1.33680%"}, {"nextFundingRate": -0.000427, "nextFundingTime": "2020-08-08T14:00:00+00:00", "name": "DOT-PERP", "24hrate": "-1.02480%"}, {"nextFundingRate": -0.000406, "nextFundingTime": "2020-08-08T14:00:00+00:00", "name": "BTMX-PERP", "24hrate": "-0.974400%"}, {"nextFundingRate": -0.000335, "nextFundingTime": "2020-08-08T14:00:00+00:00", "name": "BAL-PERP", "24hrate": "-0.804000%"}, {"nextFundingRate": 0.000206, "nextFundingTime": "2020-08-08T14:00:00+00:00", "name": "SOL-PERP", "24hrate": "0.494400%"}, {"nextFundingRate": -0.000178, "nextFundingTime": "2020-08-08T14:00:00+00:00", "name": "BNB-PERP", "24hrate": "-0.427200%"}, {"nextFundingRate": 0.00017, "nextFundingTime": "2020-08-08T14:00:00+00:00", "name": "LEO-PERP", "24hrate": "0.408000%"}, {"nextFundingRate": -0.000149, "nextFundingTime": "2020-08-08T14:00:00+00:00", "name": "TRYB-PERP", "24hrate": "-0.357600%"}, {"nextFundingRate": 0.000131, "nextFundingTime": "2020-08-08T14:00:00+00:00", "name": "DEFI-PERP", "24hrate": "0.314400%"}, {"nextFundingRate": 0.000107, "nextFundingTime": "2020-08-08T14:00:00+00:00", "name": "DRGN-PERP", "24hrate": "0.256800%"}, {"nextFundingRate": 0.000103, "nextFundingTime": "2020-08-08T14:00:00+00:00", "name": "OKB-PERP", "24hrate": "0.247200%"}, {"nextFundingRate": -9.8e-05, "nextFundingTime": "2020-08-08T14:00:00+00:00", "name": "BRZ-PERP", "24hrate": "-0.235200%"}, {"nextFundingRate": 9.6e-05, "nextFundingTime": "2020-08-08T14:00:00+00:00", "name": "SXP-PERP", "24hrate": "0.230400%"}, {"nextFundingRate": -9e-05, "nextFundingTime": "2020-08-08T14:00:00+00:00", "name": "XAUT-PERP", "24hrate": "-0.216000%"}, {"nextFundingRate": 8.3e-05, "nextFundingTime": "2020-08-08T14:00:00+00:00", "name": "DOGE-PERP", "24hrate": "0.199200%"}, {"nextFundingRate": 7.8e-05, "nextFundingTime": "2020-08-08T14:00:00+00:00", "name": "THETA-PERP", "24hrate": "0.187200%"}, {"nextFundingRate": 6.8e-05, "nextFundingTime": "2020-08-08T14:00:00+00:00", "name": "BSV-PERP", "24hrate": "0.163200%"}, {"nextFundingRate": 6.3e-05, "nextFundingTime": "2020-08-08T14:00:00+00:00", "name": "RUNE-PERP", "24hrate": "0.151200%"}, {"nextFundingRate": 5.9e-05, "nextFundingTime": "2020-08-08T14:00:00+00:00", "name": "XTZ-PERP", "24hrate": "0.141600%"}]