[{"nextFundingRate": 0.000743, "nextFundingTime": "2020-07-19T01:00:00+00:00", "name": "DMG-PERP", "24hrate": "1.78320%"}, {"nextFundingRate": 0.000209, "nextFundingTime": "2020-07-19T01:00:00+00:00", "name": "TOMO-PERP", "24hrate": "0.501600%"}, {"nextFundingRate": -0.000192, "nextFundingTime": "2020-07-19T01:00:00+00:00", "name": "LEO-PERP", "24hrate": "-0.460800%"}, {"nextFundingRate": 0.000181, "nextFundingTime": "2020-07-19T01:00:00+00:00", "name": "TRYB-PERP", "24hrate": "0.434400%"}, {"nextFundingRate": 0.000167, "nextFundingTime": "2020-07-19T01:00:00+00:00", "name": "COMP-PERP", "24hrate": "0.400800%"}, {"nextFundingRate": -0.000121, "nextFundingTime": "2020-07-19T01:00:00+00:00", "name": "BRZ-PERP", "24hrate": "-0.290400%"}, {"nextFundingRate": 0.000107, "nextFundingTime": "2020-07-19T01:00:00+00:00", "name": "BTMX-PERP", "24hrate": "0.256800%"}, {"nextFundingRate": -9.9e-05, "nextFundingTime": "2020-07-19T01:00:00+00:00", "name": "SHIT-PERP", "24hrate": "-0.237600%"}, {"nextFundingRate": -9.5e-05, "nextFundingTime": "2020-07-19T01:00:00+00:00", "name": "BAL-PERP", "24hrate": "-0.228000%"}, {"nextFundingRate": -9.3e-05, "nextFundingTime": "2020-07-19T01:00:00+00:00", "name": "DOGE-PERP", "24hrate": "-0.223200%"}, {"nextFundingRate": -8.6e-05, "nextFundingTime": "2020-07-19T01:00:00+00:00", "name": "DOT-PERP", "24hrate": "-0.206400%"}, {"nextFundingRate": 7.7e-05, "nextFundingTime": "2020-07-19T01:00:00+00:00", "name": "THETA-PERP", "24hrate": "0.184800%"}, {"nextFundingRate": -7e-05, "nextFundingTime": "2020-07-19T01:00:00+00:00", "name": "MID-PERP", "24hrate": "-0.168000%"}, {"nextFundingRate": -5.9e-05, "nextFundingTime": "2020-07-19T01:00:00+00:00", "name": "ATOM-PERP", "24hrate": "-0.141600%"}, {"nextFundingRate": 5.9e-05, "nextFundingTime": "2020-07-19T01:00:00+00:00", "name": "PRIV-PERP", "24hrate": "0.141600%"}, {"nextFundingRate": -5.9e-05, "nextFundingTime": "2020-07-19T01:00:00+00:00", "name": "SXP-PERP", "24hrate": "-0.141600%"}, {"nextFundingRate": 5.7e-05, "nextFundingTime": "2020-07-19T01:00:00+00:00", "name": "MKR-PERP", "24hrate": "0.136800%"}, {"nextFundingRate": 4.3e-05, "nextFundingTime": "2020-07-19T01:00:00+00:00", "name": "XTZ-PERP", "24hrate": "0.103200%"}, {"nextFundingRate": -3.9e-05, "nextFundingTime": "2020-07-19T01:00:00+00:00", "name": "LINK-PERP", "24hrate": "-0.0936000%"}, {"nextFundingRate": 3.5e-05, "nextFundingTime": "2020-07-19T01:00:00+00:00", "name": "KNC-PERP", "24hrate": "0.0840000%"}]