[{"nextFundingRate": 0.000527, "nextFundingTime": "2020-07-20T12:00:00+00:00", "name": "BAL-PERP", "24hrate": "1.26480%"}, {"nextFundingRate": 0.000265, "nextFundingTime": "2020-07-20T12:00:00+00:00", "name": "RUNE-PERP", "24hrate": "0.636000%"}, {"nextFundingRate": 0.000265, "nextFundingTime": "2020-07-20T12:00:00+00:00", "name": "SXP-PERP", "24hrate": "0.636000%"}, {"nextFundingRate": 0.000216, "nextFundingTime": "2020-07-20T12:00:00+00:00", "name": "TOMO-PERP", "24hrate": "0.518400%"}, {"nextFundingRate": 0.00018, "nextFundingTime": "2020-07-20T12:00:00+00:00", "name": "TRYB-PERP", "24hrate": "0.432000%"}, {"nextFundingRate": 0.000178, "nextFundingTime": "2020-07-20T12:00:00+00:00", "name": "DOT-PERP", "24hrate": "0.427200%"}, {"nextFundingRate": 0.000158, "nextFundingTime": "2020-07-20T12:00:00+00:00", "name": "BTMX-PERP", "24hrate": "0.379200%"}, {"nextFundingRate": -0.000126, "nextFundingTime": "2020-07-20T12:00:00+00:00", "name": "BRZ-PERP", "24hrate": "-0.302400%"}, {"nextFundingRate": 0.000105, "nextFundingTime": "2020-07-20T12:00:00+00:00", "name": "XTZ-PERP", "24hrate": "0.252000%"}, {"nextFundingRate": 9.9e-05, "nextFundingTime": "2020-07-20T12:00:00+00:00", "name": "EXCH-PERP", "24hrate": "0.237600%"}, {"nextFundingRate": 8.6e-05, "nextFundingTime": "2020-07-20T12:00:00+00:00", "name": "BNB-PERP", "24hrate": "0.206400%"}, {"nextFundingRate": 7.7e-05, "nextFundingTime": "2020-07-20T12:00:00+00:00", "name": "ATOM-PERP", "24hrate": "0.184800%"}, {"nextFundingRate": 7.4e-05, "nextFundingTime": "2020-07-20T12:00:00+00:00", "name": "THETA-PERP", "24hrate": "0.177600%"}, {"nextFundingRate": 7.2e-05, "nextFundingTime": "2020-07-20T12:00:00+00:00", "name": "KNC-PERP", "24hrate": "0.172800%"}, {"nextFundingRate": -6.6e-05, "nextFundingTime": "2020-07-20T12:00:00+00:00", "name": "DOGE-PERP", "24hrate": "-0.158400%"}, {"nextFundingRate": -6.1e-05, "nextFundingTime": "2020-07-20T12:00:00+00:00", "name": "MID-PERP", "24hrate": "-0.146400%"}, {"nextFundingRate": 6e-05, "nextFundingTime": "2020-07-20T12:00:00+00:00", "name": "DMG-PERP", "24hrate": "0.144000%"}, {"nextFundingRate": 4.8e-05, "nextFundingTime": "2020-07-20T12:00:00+00:00", "name": "COMP-PERP", "24hrate": "0.115200%"}, {"nextFundingRate": -4.7e-05, "nextFundingTime": "2020-07-20T12:00:00+00:00", "name": "ALGO-PERP", "24hrate": "-0.112800%"}, {"nextFundingRate": 4.7e-05, "nextFundingTime": "2020-07-20T12:00:00+00:00", "name": "DEFI-PERP", "24hrate": "0.112800%"}]