[{"nextFundingRate": 0.001076, "nextFundingTime": "2020-07-31T09:00:00+00:00", "name": "MTA-PERP", "24hrate": "2.58240%"}, {"nextFundingRate": 0.000547, "nextFundingTime": "2020-07-31T09:00:00+00:00", "name": "AMPL-PERP", "24hrate": "1.31280%"}, {"nextFundingRate": 0.000319, "nextFundingTime": "2020-07-31T09:00:00+00:00", "name": "BAL-PERP", "24hrate": "0.765600%"}, {"nextFundingRate": 0.000263, "nextFundingTime": "2020-07-31T09:00:00+00:00", "name": "DOT-PERP", "24hrate": "0.631200%"}, {"nextFundingRate": 0.000241, "nextFundingTime": "2020-07-31T09:00:00+00:00", "name": "SOL-PERP", "24hrate": "0.578400%"}, {"nextFundingRate": 0.000226, "nextFundingTime": "2020-07-31T09:00:00+00:00", "name": "TOMO-PERP", "24hrate": "0.542400%"}, {"nextFundingRate": 0.000197, "nextFundingTime": "2020-07-31T09:00:00+00:00", "name": "TRYB-PERP", "24hrate": "0.472800%"}, {"nextFundingRate": 0.000192, "nextFundingTime": "2020-07-31T09:00:00+00:00", "name": "PAXG-PERP", "24hrate": "0.460800%"}, {"nextFundingRate": 0.000191, "nextFundingTime": "2020-07-31T09:00:00+00:00", "name": "SXP-PERP", "24hrate": "0.458400%"}, {"nextFundingRate": 0.00019, "nextFundingTime": "2020-07-31T09:00:00+00:00", "name": "RUNE-PERP", "24hrate": "0.456000%"}, {"nextFundingRate": 0.000155, "nextFundingTime": "2020-07-31T09:00:00+00:00", "name": "DMG-PERP", "24hrate": "0.372000%"}, {"nextFundingRate": 0.00015, "nextFundingTime": "2020-07-31T09:00:00+00:00", "name": "KNC-PERP", "24hrate": "0.360000%"}, {"nextFundingRate": 0.000145, "nextFundingTime": "2020-07-31T09:00:00+00:00", "name": "XAUT-PERP", "24hrate": "0.348000%"}, {"nextFundingRate": 0.00013, "nextFundingTime": "2020-07-31T09:00:00+00:00", "name": "MKR-PERP", "24hrate": "0.312000%"}, {"nextFundingRate": 0.000119, "nextFundingTime": "2020-07-31T09:00:00+00:00", "name": "ATOM-PERP", "24hrate": "0.285600%"}, {"nextFundingRate": 0.000119, "nextFundingTime": "2020-07-31T09:00:00+00:00", "name": "LEO-PERP", "24hrate": "0.285600%"}, {"nextFundingRate": 0.000111, "nextFundingTime": "2020-07-31T09:00:00+00:00", "name": "MID-PERP", "24hrate": "0.266400%"}, {"nextFundingRate": 9.9e-05, "nextFundingTime": "2020-07-31T09:00:00+00:00", "name": "DRGN-PERP", "24hrate": "0.237600%"}, {"nextFundingRate": 9.5e-05, "nextFundingTime": "2020-07-31T09:00:00+00:00", "name": "VET-PERP", "24hrate": "0.228000%"}, {"nextFundingRate": 9.4e-05, "nextFundingTime": "2020-07-31T09:00:00+00:00", "name": "DEFI-PERP", "24hrate": "0.225600%"}]